QMultiAdapt/__init__.py
QMultiAdapt/ansatz.py
QMultiAdapt/ansatzVect.py
QMultiAdapt/effh.py
QMultiAdapt/solver.py
QMultiAdapt-2.0.0.dist-info/LICENSE
QMultiAdapt-2.0.0.dist-info/METADATA
QMultiAdapt-2.0.0.dist-info/WHEEL
QMultiAdapt-2.0.0.dist-info/top_level.txt
QMultiAdapt-2.0.0.dist-info/RECORD
