Metadata-Version: 2.1
Name: QMultiAdapt
Version: 2.0.0
Summary: A package for adaptive variational quantum computing algorithms
Home-page: https://github.com/saurabhshivpuje/QMultiAdapt
Author: Saurabh Shivpuje
Author-email: saushivpuje@gmail.com
License: MIT
Classifier: Programming Language :: Python :: 3
Classifier: License :: OSI Approved :: MIT License
Classifier: Operating System :: OS Independent
Requires-Python: >=3.6
License-File: LICENSE
Requires-Dist: numpy
Requires-Dist: scipy
Requires-Dist: matplotlib
